[
  {
    "administrativeDivision": "峨眉鄉",
    "village": "總計",
    "candidateVotes": {
      "rainforest": 144,
      "coast": 1882,
      "savannah": 1593
    },
    "validVotes": 3619,
    "invalidVotes": 38,
    "totalVotes": 3657,
    "receivedUnvoted": 0,
    "issuedVotes": 3657,
    "remainingVotes": 1190,
    "eligibleVoters": 4847,
    "voterTurnout": 75.4487
  },
  {
    "administrativeDivision": "峨眉鄉",
    "village": "峨眉村",
    "candidateVotes": {
      "rainforest": 31,
      "coast": 372,
      "savannah": 235
    },
    "validVotes": 638,
    "invalidVotes": 9,
    "totalVotes": 647,
    "receivedUnvoted": 0,
    "issuedVotes": 647,
    "remainingVotes": 182,
    "eligibleVoters": 829,
    "voterTurnout": 78.0458
  },
  {
    "administrativeDivision": "峨眉鄉",
    "village": "中盛村",
    "candidateVotes": {
      "rainforest": 15,
      "coast": 231,
      "savannah": 259
    },
    "validVotes": 505,
    "invalidVotes": 8,
    "totalVotes": 513,
    "receivedUnvoted": 0,
    "issuedVotes": 513,
    "remainingVotes": 145,
    "eligibleVoters": 658,
    "voterTurnout": 77.9635
  },
  {
    "administrativeDivision": "峨眉鄉",
    "village": "石井村",
    "candidateVotes": {
      "rainforest": 16,
      "coast": 236,
      "savannah": 184
    },
    "validVotes": 436,
    "invalidVotes": 4,
    "totalVotes": 440,
    "receivedUnvoted": 0,
    "issuedVotes": 440,
    "remainingVotes": 139,
    "eligibleVoters": 579,
    "voterTurnout": 75.9931
  },
  {
    "administrativeDivision": "峨眉鄉",
    "village": "七星村",
    "candidateVotes": {
      "rainforest": 12,
      "coast": 231,
      "savannah": 212
    },
    "validVotes": 455,
    "invalidVotes": 3,
    "totalVotes": 458,
    "receivedUnvoted": 0,
    "issuedVotes": 458,
    "remainingVotes": 136,
    "eligibleVoters": 594,
    "voterTurnout": 77.1044
  },
  {
    "administrativeDivision": "峨眉鄉",
    "village": "富興村",
    "candidateVotes": {
      "rainforest": 44,
      "coast": 495,
      "savannah": 418
    },
    "validVotes": 957,
    "invalidVotes": 5,
    "totalVotes": 962,
    "receivedUnvoted": 0,
    "issuedVotes": 962,
    "remainingVotes": 392,
    "eligibleVoters": 1354,
    "voterTurnout": 71.0487
  },
  {
    "administrativeDivision": "峨眉鄉",
    "village": "湖光村",
    "candidateVotes": {
      "rainforest": 26,
      "coast": 317,
      "savannah": 285
    },
    "validVotes": 628,
    "invalidVotes": 9,
    "totalVotes": 637,
    "receivedUnvoted": 0,
    "issuedVotes": 637,
    "remainingVotes": 196,
    "eligibleVoters": 833,
    "voterTurnout": 76.4706
  }
]